{
  "format_version": "1.12",
  "minecraft:recipe_shaped": {
    "description": {
      "identifier": "dp_foods_plus:crsbcraft"
    },
    "groups": [
      "dp_foods_plus"
    ],
    "tags": [
      "crafting_table"
    ],
    "pattern": [
      " 1 ",
      "345",
      " 7 "
    ],
    "key": {
      "1": {
        "item": "minecraft:sugar"
      },
      "3": {
        "item": "dp_foods_plus:chocolate"
      },
      "4": {
        "item": "dp_foods_plus:peach"
      },
      "5": {
        "item": "dp_foods_plus:dough"
      },
      "7": {
        "item": "dp_foods_plus:dough"
      }
    },
    "result": {
      "item": "dp_foods_plus:chocolate_raspberry_brownies",
      "count": 1
    }
  }
}