[
    {
        "pack_id": "c8ba9394-c483-4b7b-acac-c53685113b6d",
        "version": [
            8,
            2,
            1
        ]
    },
    {
        "pack_id": "7c094808-58aa-11e9-8647-d663bd873d93",
        "version": [
            1,
            4,
            1
        ]
    },
    {
        "pack_id": "3a11b3ea-af6b-48e0-9524-e76104f8ca1d",
        "version": [
            1,
            7,
            0
        ]
    },
    {
        "pack_id": "a35df803-69be-39de-b680-b1a6f6188bc5",
        "version": [
            1,
            1,
            5
        ]
    }
]